digsim/__init__.py
digsim/app/__main__.py
digsim/app/cli.py
digsim/app/gui/__init__.py
digsim/app/gui/_circuit_area.py
digsim/app/gui/_component_selection.py
digsim/app/gui/_main_window.py
digsim/app/gui/_top_bar.py
digsim/app/gui/_utils.py
digsim/app/gui/_warning_dialog.py
digsim/app/gui_objects/__init__.py
digsim/app/gui_objects/_bus_bit_object.py
digsim/app/gui_objects/_buzzer_object.py
digsim/app/gui_objects/_component_context_menu.py
digsim/app/gui_objects/_component_object.py
digsim/app/gui_objects/_component_port_item.py
digsim/app/gui_objects/_dip_switch_object.py
digsim/app/gui_objects/_gui_note_object.py
digsim/app/gui_objects/_gui_object_factory.py
digsim/app/gui_objects/_hexdigit_object.py
digsim/app/gui_objects/_image_objects.py
digsim/app/gui_objects/_label_object.py
digsim/app/gui_objects/_logic_analyzer_object.py
digsim/app/gui_objects/_seven_segment_object.py
digsim/app/gui_objects/_shortcut_objects.py
digsim/app/gui_objects/_yosys_object.py
digsim/app/gui_objects/images/AND.png
digsim/app/gui_objects/images/Analyzer.png
digsim/app/gui_objects/images/BUF.png
digsim/app/gui_objects/images/Buzzer.png
digsim/app/gui_objects/images/Clock.png
digsim/app/gui_objects/images/DFF.png
digsim/app/gui_objects/images/DIP_SWITCH.png
digsim/app/gui_objects/images/FlipFlop.png
digsim/app/gui_objects/images/IC.png
digsim/app/gui_objects/images/LED_OFF.png
digsim/app/gui_objects/images/LED_ON.png
digsim/app/gui_objects/images/MUX.png
digsim/app/gui_objects/images/NAND.png
digsim/app/gui_objects/images/NOR.png
digsim/app/gui_objects/images/NOT.png
digsim/app/gui_objects/images/ONE.png
digsim/app/gui_objects/images/OR.png
digsim/app/gui_objects/images/PB.png
digsim/app/gui_objects/images/Switch_OFF.png
digsim/app/gui_objects/images/Switch_ON.png
digsim/app/gui_objects/images/XNOR.png
digsim/app/gui_objects/images/XOR.png
digsim/app/gui_objects/images/YOSYS.png
digsim/app/gui_objects/images/ZERO.png
digsim/app/images/app_icon.png
digsim/app/model/__init__.py
digsim_logic_simulator-0.22.0.dist-info/licenses/LICENSE.md
digsim_logic_simulator-0.22.0.dist-info/METADATA
digsim_logic_simulator-0.22.0.dist-info/WHEEL
digsim_logic_simulator-0.22.0.dist-info/entry_points.txt
digsim_logic_simulator-0.22.0.dist-info/top_level.txt
digsim_logic_simulator-0.22.0.dist-info/RECORD
