Metadata-Version: 2.4
Name: digsim-logic-simulator
Version: 0.22.0
Summary: Interactive Digital Logic Simulator
Author-email: Fredrik Andersson <freand@gmail.com>
Maintainer-email: Fredrik Andersson <freand@gmail.com>
Project-URL: homepage, https://github.com/freand76/digsim
Keywords: educational,simulation,digital
Classifier: Development Status :: 5 - Production/Stable
Classifier: Programming Language :: Python :: 3
Classifier: Programming Language :: Python :: 3.10
Classifier: Programming Language :: Python :: 3.11
Classifier: Programming Language :: Python :: 3.12
Classifier: Programming Language :: Python :: 3.13
Classifier: Programming Language :: Python :: 3.14
Classifier: Programming Language :: Python :: 3 :: Only
Requires-Python: >=3.10
License-File: LICENSE.md
Requires-Dist: pyvcd==0.4.1
Requires-Dist: pyside6==6.10.1
Requires-Dist: pexpect==4.9.0
Requires-Dist: pydantic==2.12.5
Requires-Dist: qtawesome==1.4.0
Requires-Dist: yowasp-yosys==0.60.0.0.post1055
Dynamic: license-file
